bs_hsv/__init__.py
bs_hsv/core.py
bs_hsv/exceptions.py
bs_hsv/generators.py
bs_hsv/utils.py
bs_hsv-1.0.1.dist-info/METADATA
bs_hsv-1.0.1.dist-info/WHEEL
bs_hsv-1.0.1.dist-info/top_level.txt
bs_hsv-1.0.1.dist-info/RECORD
