Metadata-Version: 2.4
Name: bs-hsv
Version: 1.0.1
Summary: A Pydantic-based module for hit score vizualizer presets
Home-page: https://github.com/CodeSoftGit/bs-hsv
Author: CodeSoftGit
Project-URL: Bug Tracker, https://github.com/CodeSoftGit/bs-hsv/issues
Project-URL: Documentation, https://github.com/CodeSoftGit/bs-hsv#readme
Project-URL: Source Code, https://github.com/CodeSoftGit/bs-hsv
Keywords: hit score,visualization,game development,pydantic,text art,beat saber,beatsaber
Classifier: Development Status :: 4 - Beta
Classifier: Intended Audience :: Developers
Classifier: License :: OSI Approved :: MIT License
Classifier: Programming Language :: Python :: 3
Classifier: Programming Language :: Python :: 3.8
Classifier: Programming Language :: Python :: 3.9
Classifier: Programming Language :: Python :: 3.10
Classifier: Programming Language :: Python :: 3.11
Classifier: Programming Language :: Python :: 3.12
Classifier: Programming Language :: Python :: 3.13
Classifier: Operating System :: OS Independent
Classifier: Topic :: Software Development :: Libraries :: Python Modules
Requires-Python: >=3.8
Requires-Dist: pydantic>=2.0.0
Requires-Dist: pillow>=9.0.0
Requires-Dist: numpy>=1.20.0
Dynamic: author
Dynamic: classifier
Dynamic: description
Dynamic: description-content-type
Dynamic: home-page
Dynamic: keywords
Dynamic: project-url
Dynamic: requires-dist
Dynamic: requires-python
Dynamic: summary
